veazy/__init__.py
veazy/cli.py
veazy/veazy.py
veazy-0.1.3.dist-info/LICENCE
veazy-0.1.3.dist-info/METADATA
veazy-0.1.3.dist-info/WHEEL
veazy-0.1.3.dist-info/entry_points.txt
veazy-0.1.3.dist-info/top_level.txt
veazy-0.1.3.dist-info/RECORD
