Metadata-Version: 2.1
Name: veazy
Version: 0.1.3
Summary: Easy way to visualise your python package
Home-page: https://gitlab.com/janscholten/veazy
Author: Xomnia14
Author-email: jan.scholten@xomnia.com
License: UNKNOWN
Platform: UNKNOWN
Classifier: Programming Language :: Python :: 3
Classifier: License :: OSI Approved :: MIT License
Classifier: Operating System :: OS Independent
Requires-Python: >=3.6
Requires-Dist: pydotplus
Requires-Dist: click
Requires-Dist: networkx
Requires-Dist: pyan3-for-veazy
